exerciseterminal/BodyHealthTerminal.py
exerciseterminal/CreateRequiredFiles.py
exerciseterminal/ExerciseTerminal.py
exerciseterminal/__init__.py
ExerciseTerminal-0.0.1.dist-info/LICENSE.txt
ExerciseTerminal-0.0.1.dist-info/METADATA
ExerciseTerminal-0.0.1.dist-info/WHEEL
ExerciseTerminal-0.0.1.dist-info/entry_points.txt
ExerciseTerminal-0.0.1.dist-info/top_level.txt
ExerciseTerminal-0.0.1.dist-info/RECORD
