Metadata-Version: 2.1
Name: ExerciseTerminal
Version: 0.0.1
Summary: A lightweight CLI application for logging exercise and body information for easy statistical analysis; created using Click.
Home-page: https://github.com/ckrat67/ExerciseTerminal
Author: Tan Yann Xu
Author-email: leejohn723@gmail.com
License: UNKNOWN
Keywords: exercise health healthy living
Platform: UNKNOWN
Classifier: Programming Language :: Python :: 3
Classifier: License :: OSI Approved :: MIT License
Classifier: Operating System :: OS Independent
Requires-Dist: Click
Requires-Dist: pandas (==1.0.3)
Requires-Dist: datetime
